LICENSE.txt
MANIFEST.in
README.rst
requirements.txt
setup.cfg
setup.py
scriptler/__init__.py
scriptler/__main__.py
scriptler/cli.py
scriptler/config.py
scriptler/model.py
scriptler/scripts.py
scriptler/sources.py
scriptler/yaml.py
scriptler.egg-info/PKG-INFO
scriptler.egg-info/SOURCES.txt
scriptler.egg-info/dependency_links.txt
scriptler.egg-info/entry_points.txt
scriptler.egg-info/requires.txt
scriptler.egg-info/top_level.txt