Metadata-Version: 1.1
Name: scriptler
Version: 1.4.0
Summary: manage scripts from different sources
Home-page: https://www.github.com/afriemann/scriptler
Author: Aljosha Friemann
Author-email: a.friemann@automate.wtf
License: /*
